jsinfer/__init__.py
jsinfer/client.py
jsinfer/py.typed
jsinfer-0.2.1.dist-info/WHEEL
jsinfer-0.2.1.dist-info/METADATA
jsinfer-0.2.1.dist-info/RECORD
