Metadata-Version: 2.3
Name: jsinfer
Version: 0.2.1
Summary: Client API for dormant puzzle inference!
Requires-Dist: aiofiles>=25.1.0
Requires-Dist: aiohttp>=3.13.2
Requires-Dist: numpy>=2.0.2
Requires-Python: >=3.9
